{
  "gameweeks": {
    "1": {
      "url": "https://1b0s3gmik3fqhcvt.public.blob.vercel-storage.com/fpl_rosters_points_gw1-d884e3e39a.csv",
      "hash": "d884e3e39a9f182f401633139a54d75e",
      "timestamp": 1767120742,
      "updated": "2025-12-30T18:52:22.643795Z"
    },
    "2": {
      "url": "https://1b0s3gmik3fqhcvt.public.blob.vercel-storage.com/fpl_rosters_points_gw2-293cf06bcc.csv",
      "hash": "293cf06bcc45683d3248eaa020b8dc1b",
      "timestamp": 1767120790,
      "updated": "2025-12-30T18:53:10.921158Z"
    },
    "3": {
      "url": "https://1b0s3gmik3fqhcvt.public.blob.vercel-storage.com/fpl_rosters_points_gw3-df0d6ac820.csv",
      "hash": "df0d6ac82088fec11f8773df63c2be2f",
      "timestamp": 1767120941,
      "updated": "2025-12-30T18:55:41.779329Z"
    },
    "4": {
      "url": "https://1b0s3gmik3fqhcvt.public.blob.vercel-storage.com/fpl_rosters_points_gw4-98e16b6e5d.csv",
      "hash": "98e16b6e5d3813d7054c41e864005b54",
      "timestamp": 1766760296,
      "updated": "2025-12-26T14:44:56.709266Z"
    },
    "5": {
      "url": "https://1b0s3gmik3fqhcvt.public.blob.vercel-storage.com/fpl_rosters_points_gw5-04af1887aa.csv",
      "hash": "04af1887aa720142674080113f539a68",
      "timestamp": 1766786244,
      "updated": "2025-12-26T21:57:24.770248Z"
    },
    "6": {
      "url": "https://1b0s3gmik3fqhcvt.public.blob.vercel-storage.com/fpl_rosters_points_gw6-d356472517.csv",
      "hash": "d356472517525a91c03978e8783f4312",
      "timestamp": 1766786539,
      "updated": "2025-12-26T22:02:19.709006Z"
    },
    "7": {
      "url": "https://1b0s3gmik3fqhcvt.public.blob.vercel-storage.com/fpl_rosters_points_gw7-8fd05f7e1d.csv",
      "hash": "8fd05f7e1d2ccc01803a2895d0e4b1a2",
      "timestamp": 1767120826,
      "updated": "2025-12-30T18:53:46.436269Z"
    },
    "8": {
      "url": "https://1b0s3gmik3fqhcvt.public.blob.vercel-storage.com/fpl_rosters_points_gw8-dc8928136e.csv",
      "hash": "dc8928136e1f9c2ce6dc860bafaa706d",
      "timestamp": 1766764027,
      "updated": "2025-12-26T15:47:07.565290Z"
    },
    "9": {
      "url": "https://1b0s3gmik3fqhcvt.public.blob.vercel-storage.com/fpl_rosters_points_gw9-70fe3672b0.csv",
      "hash": "70fe3672b0f3cdb9eca4b4d6f31264b3",
      "timestamp": 1766759298,
      "updated": "2025-12-26T14:28:18.735428Z"
    },
    "10": {
      "url": "https://1b0s3gmik3fqhcvt.public.blob.vercel-storage.com/fpl_rosters_points_gw10-3463f98ca8.csv",
      "hash": "3463f98ca83ccced3fd2c9aa0a91a4d5",
      "timestamp": 1767120847,
      "updated": "2025-12-30T18:54:07.566713Z"
    },
    "11": {
      "url": "https://1b0s3gmik3fqhcvt.public.blob.vercel-storage.com/fpl_rosters_points_gw11-57038411dc.csv",
      "hash": "57038411dccb95a7acfa74ab80a9b9ed",
      "timestamp": 1767116682,
      "updated": "2025-12-30T17:44:42.346170Z"
    },
    "12": {
      "url": "https://1b0s3gmik3fqhcvt.public.blob.vercel-storage.com/fpl_rosters_points_gw12-e3b16257de.csv",
      "hash": "e3b16257deea39b1ca13788e29f4155a",
      "timestamp": 1766762909,
      "updated": "2025-12-26T15:28:29.764208Z"
    },
    "13": {
      "url": "https://1b0s3gmik3fqhcvt.public.blob.vercel-storage.com/fpl_rosters_points_gw13-ea086e4a3d.csv",
      "hash": "ea086e4a3d5762cec616e4509b470887",
      "timestamp": 1766762660,
      "updated": "2025-12-26T15:24:20.158685Z"
    },
    "14": {
      "url": "https://1b0s3gmik3fqhcvt.public.blob.vercel-storage.com/fpl_rosters_points_gw14-4451666433.csv",
      "hash": "44516664334f5733d7e22ae39019f3b0",
      "timestamp": 1766759308,
      "updated": "2025-12-26T14:28:28.424890Z"
    },
    "15": {
      "url": "https://1b0s3gmik3fqhcvt.public.blob.vercel-storage.com/fpl_rosters_points_gw15-7fdac09599.csv",
      "hash": "7fdac09599d8be418fcf1f91bcf4f6bb",
      "timestamp": 1766759310,
      "updated": "2025-12-26T14:28:30.182746Z"
    },
    "16": {
      "url": "https://1b0s3gmik3fqhcvt.public.blob.vercel-storage.com/fpl_rosters_points_gw16-be58a0b8f3.csv",
      "hash": "be58a0b8f391454615eb4829ebf5dc94",
      "timestamp": 1767120889,
      "updated": "2025-12-30T18:54:49.842417Z"
    },
    "17": {
      "url": "https://1b0s3gmik3fqhcvt.public.blob.vercel-storage.com/fpl_rosters_points_gw17-d873014d57.csv",
      "hash": "d873014d5745f16bd92188cbafeca077",
      "timestamp": 1767120961,
      "updated": "2025-12-30T18:56:01.033935Z"
    },
    "18": {
      "url": "https://1b0s3gmik3fqhcvt.public.blob.vercel-storage.com/fpl_rosters_points_gw18-04df8c383c.csv",
      "hash": "04df8c383cde323d6524c36e380bce13",
      "timestamp": 1767116696,
      "updated": "2025-12-30T17:44:56.749358Z"
    },
    "19": {
      "url": "https://1b0s3gmik3fqhcvt.public.blob.vercel-storage.com/fpl_rosters_points_gw19.csv",
      "hash": "54ae7a0ec2ebb19d6de7b50d45a482ee",
      "timestamp": 1767121078,
      "updated": "2025-12-30T13:57:58.998550Z"
    }
  },
  "updated": "2025-12-30T18:56:01.033946Z",
  "version": "1767120962",
  "timestamp": 1767120961,
  "latest_gw": 19
}